custom_decorator/__init__.py
custom_decorator/singleton/README.md
custom_decorator/singleton/__init__.py
custom_decorator/singleton/singleton.py
xhm_chat_memory/README.md
xhm_chat_memory/__init__.py
xhm_chat_memory/chat_memory.py
xhm_chat_memory/chat_message.py
xhm_config/.gitignore
xhm_config/README.md
xhm_config/__init__.py
xhm_config/application.toml
xhm_config/config.py
xhm_config/llm_config.py
xhm_config/sdk_secrets.toml
xhm_config/sdk_settings.toml
xhm_html2image/MinIOClient.py
xhm_html2image/README.md
xhm_html2image/__init__.py
xhm_html2image/html2image.py
xhm_html2image/template_rich.html
xhm_log/README.md
xhm_log/__init__.py
xhm_mq/README.md
xhm_mq/__init__.py
xhm_mq/rabbitmq_consumer.py
xhm_mq/rabbitmq_producer.py
xhm_notify/EmailSender.py
xhm_notify/__init__.py
xhm_redis/README.md
xhm_redis/__init__.py
xhm_redis/xhm_redis.py
xhm_util/__init__.py
xhm_util/image_util.py
xhm_util/url_util.py
xhm_all-0.0.9.dist-info/METADATA
xhm_all-0.0.9.dist-info/WHEEL
xhm_all-0.0.9.dist-info/RECORD
