Metadata-Version: 2.1
Name: xhm_all
Version: 0.0.9
Summary: xhm python sdk
License: MIT
Author: 邹慧刚
Author-email: 952750120@qq.com
Requires-Python: >=3.10,<4.0
Classifier: License :: OSI Approved :: MIT License
Classifier: Programming Language :: Python :: 3
Classifier: Programming Language :: Python :: 3.10
Classifier: Programming Language :: Python :: 3.11
Classifier: Programming Language :: Python :: 3.12
Requires-Dist: dspy-ai (==2.5.7)
Requires-Dist: dynaconf (>=3.1.0,<4.0.0)
